strangenameahaha/__init__.py
strangenameahaha/__main__.py
strangenameahaha/report.py
strangenameahaha-0.1.2.dist-info/METADATA
strangenameahaha-0.1.2.dist-info/WHEEL
strangenameahaha-0.1.2.dist-info/top_level.txt
strangenameahaha-0.1.2.dist-info/RECORD
