Metadata-Version: 2.1
Name: strangenameahaha
Version: 0.1.2
Summary: Python-пакет, который будет анализировать данные о клиентах и генерировать подробный отчёт
Author-email: Savva Serebriakov <savva08savva08@gmail.com>
License: MIT
Requires-Python: >=3.8
